<?xml version="1.0"?>
<PlanetData Name="Earth">
  <SceneObjectBuilder xmlns:xsd="http://www.w3.org/2001/XMLSchema" xmlns:xsi="http://www.w3.org/2001/XMLSchema-instance" xsi:type="DefaultSceneObjectBuilder" />
  <Modules>
    <ModuleData xmlns:xsd="http://www.w3.org/2001/XMLSchema" xmlns:xsi="http://www.w3.org/2001/XMLSchema-instance" xsi:type="GravityModuleData">
      <Mass>1</Mass>
      <Position>
        <x>8.16</x>
        <y>0</y>
      </Position>
      <Velocity>
        <x>0</x>
        <y>11</y>
      </Velocity>
    </ModuleData>
    <ModuleData xmlns:xsd="http://www.w3.org/2001/XMLSchema" xmlns:xsi="http://www.w3.org/2001/XMLSchema-instance" xsi:type="PlanetViewModuleData">
      <Scale>1.6</Scale>
      <MeshProvider>
        <NoiseSettings>
          <Frequency>3</Frequency>
          <Lacunarity>7.45</Lacunarity>
          <Persistence>0.2</Persistence>
          <Vector3>
            <x>0</x>
            <y>0</y>
            <z>0</z>
          </Vector3>
          <Octaves>3</Octaves>
          <MinValue>0.5</MinValue>
          <Strength>0.2</Strength>
        </NoiseSettings>
      </MeshProvider>
      <MaterialProvider>
        <LandGradient>
          <colorKeys>
            <GradientColorKey>
              <color>
                <r>0.241723046</r>
                <g>0.290839344</g>
                <b>0.5283019</b>
                <a>1</a>
              </color>
              <time>0.0205844212</time>
            </GradientColorKey>
            <GradientColorKey>
              <color>
                <r>0.8102928</r>
                <g>0.8518696</g>
                <b>0.5183358</b>
                <a>1</a>
              </color>
              <time>0.07058824</time>
            </GradientColorKey>
            <GradientColorKey>
              <color>
                <r>0.490993232</r>
                <g>0.6037736</g>
                <b>0.116767526</b>
                <a>1</a>
              </color>
              <time>0.126466781</time>
            </GradientColorKey>
            <GradientColorKey>
              <color>
                <r>0.6320754</r>
                <g>0.5237532</g>
                <b>0.432315737</b>
                <a>1</a>
              </color>
              <time>0.2264744</time>
            </GradientColorKey>
            <GradientColorKey>
              <color>
                <r>0.5283019</r>
                <g>0.23447977</g>
                <b>0.196867213</b>
                <a>1</a>
              </color>
              <time>0.329411775</time>
            </GradientColorKey>
            <GradientColorKey>
              <color>
                <r>0.46226418</r>
                <g>0.46226418</g>
                <b>0.46226418</b>
                <a>1</a>
              </color>
              <time>0.476478219</time>
            </GradientColorKey>
            <GradientColorKey>
              <color>
                <r>0.5311368</r>
                <g>0.5311368</g>
                <b>0.5311368</b>
                <a>1</a>
              </color>
              <time>0.68235296</time>
            </GradientColorKey>
            <GradientColorKey>
              <color>
                <r>1</r>
                <g>1</g>
                <b>1</b>
                <a>1</a>
              </color>
              <time>0.958831131</time>
            </GradientColorKey>
          </colorKeys>
          <alphaKeys>
            <GradientAlphaKey>
              <alpha>1</alpha>
              <time>0.40589</time>
            </GradientAlphaKey>
            <GradientAlphaKey>
              <alpha>1</alpha>
              <time>0.544121444</time>
            </GradientAlphaKey>
            <GradientAlphaKey>
              <alpha>1</alpha>
              <time>0.6852979</time>
            </GradientAlphaKey>
          </alphaKeys>
          <mode>Blend</mode>
        </LandGradient>
        <WaterGradient>
          <colorKeys>
            <GradientColorKey>
              <color>
                <r>0.169900313</r>
                <g>0.169900313</g>
                <b>0.4339623</b>
                <a>1</a>
              </color>
              <time>0.179415584</time>
            </GradientColorKey>
            <GradientColorKey>
              <color>
                <r>0.253426462</r>
                <g>0.375818163</g>
                <b>0.6320754</b>
                <a>1</a>
              </color>
              <time>0.7882353</time>
            </GradientColorKey>
            <GradientColorKey>
              <color>
                <r>0.508632958</r>
                <g>0.6610616</g>
                <b>0.8490566</b>
                <a>1</a>
              </color>
              <time>0.9499962</time>
            </GradientColorKey>
            <GradientColorKey>
              <color>
                <r>1</r>
                <g>1</g>
                <b>1</b>
                <a>1</a>
              </color>
              <time>1</time>
            </GradientColorKey>
          </colorKeys>
          <alphaKeys>
            <GradientAlphaKey>
              <alpha>1</alpha>
              <time>0.40589</time>
            </GradientAlphaKey>
            <GradientAlphaKey>
              <alpha>1</alpha>
              <time>0.544121444</time>
            </GradientAlphaKey>
            <GradientAlphaKey>
              <alpha>1</alpha>
              <time>0.6852979</time>
            </GradientAlphaKey>
          </alphaKeys>
          <mode>Blend</mode>
        </WaterGradient>
      </MaterialProvider>
    </ModuleData>
    <ModuleData xmlns:xsd="http://www.w3.org/2001/XMLSchema" xmlns:xsi="http://www.w3.org/2001/XMLSchema-instance" xsi:type="BodyCollisionModuleData" />
  </Modules>
</PlanetData>